[{"year":2013,"standings":[{"id":"NYK","team":"New York Knicks","seed":2,"wins":54,"loses":28,"win_percentage":0.659,"games_behind":0,"points_per_game":100,"points_allowed":95.7,"simple_rating_system":3.73,"conference":"Eastern Conference","division":"Atlantic Division"},{"id":"BRK","team":"Brooklyn Nets","seed":4,"wins":49,"loses":33,"win_percentage":0.598,"games_behind":5,"points_per_game":96.9,"points_allowed":95.1,"simple_rating_system":1.25,"conference":"Eastern Conference","division":"Atlantic Division"},{"id":"BOS","team":"Boston Celtics","seed":7,"wins":41,"loses":40,"win_percentage":0.506,"games_behind":12.5,"points_per_game":96.5,"points_allowed":96.7,"simple_rating_system":-0.62,"conference":"Eastern Conference","division":"Atlantic Division"},{"id":"PHI","team":"Philadelphia 76ers","seed":9,"wins":34,"loses":48,"win_percentage":0.415,"games_behind":20,"points_per_game":93.2,"points_allowed":96.5,"simple_rating_system":-3.51,"conference":"Eastern Conference","division":"Atlantic Division"},{"id":"TOR","team":"Toronto Raptors","seed":10,"wins":34,"loses":48,"win_percentage":0.415,"games_behind":20,"points_per_game":97.2,"points_allowed":98.7,"simple_rating_system":-1.96,"conference":"Eastern Conference","division":"Atlantic Division"},{"id":"IND","team":"Indiana Pacers","seed":3,"wins":49,"loses":32,"win_percentage":0.605,"games_behind":0,"points_per_game":94.7,"points_allowed":90.7,"simple_rating_system":3.34,"conference":"Eastern Conference","division":"Central Division"},{"id":"CHI","team":"Chicago Bulls","seed":5,"wins":45,"loses":37,"win_percentage":0.549,"games_behind":4.5,"points_per_game":93.2,"points_allowed":92.9,"simple_rating_system":-0.02,"conference":"Eastern Conference","division":"Central Division"},{"id":"MIL","team":"Milwaukee Bucks","seed":8,"wins":38,"loses":44,"win_percentage":0.463,"games_behind":11.5,"points_per_game":98.9,"points_allowed":100.4,"simple_rating_system":-1.83,"conference":"Eastern Conference","division":"Central Division"},{"id":"DET","team":"Detroit Pistons","seed":11,"wins":29,"loses":53,"win_percentage":0.354,"games_behind":20.5,"points_per_game":94.9,"points_allowed":98.8,"simple_rating_system":-4.33,"conference":"Eastern Conference","division":"Central Division"},{"id":"CLE","team":"Cleveland Cavaliers","seed":13,"wins":24,"loses":58,"win_percentage":0.293,"games_behind":25.5,"points_per_game":96.5,"points_allowed":101.2,"simple_rating_system":-4.87,"conference":"Eastern Conference","division":"Central Division"},{"id":"MIA","team":"Miami Heat","seed":1,"wins":66,"loses":16,"win_percentage":0.805,"games_behind":0,"points_per_game":102.9,"points_allowed":95,"simple_rating_system":7.03,"conference":"Eastern Conference","division":"Southeast Division"},{"id":"ATL","team":"Atlanta Hawks","seed":6,"wins":44,"loses":38,"win_percentage":0.537,"games_behind":22,"points_per_game":98,"points_allowed":97.5,"simple_rating_system":-0.08,"conference":"Eastern Conference","division":"Southeast Division"},{"id":"WAS","team":"Washington Wizards","seed":12,"wins":29,"loses":53,"win_percentage":0.354,"games_behind":37,"points_per_game":93.2,"points_allowed":95.8,"simple_rating_system":-2.78,"conference":"Eastern Conference","division":"Southeast Division"},{"id":"CHA","team":"Charlotte Bobcats","seed":14,"wins":21,"loses":61,"win_percentage":0.256,"games_behind":45,"points_per_game":93.4,"points_allowed":102.7,"simple_rating_system":-9.29,"conference":"Eastern Conference","division":"Southeast Division"},{"id":"ORL","team":"Orlando Magic","seed":15,"wins":20,"loses":62,"win_percentage":0.244,"games_behind":46,"points_per_game":94.1,"points_allowed":101.1,"simple_rating_system":-7.12,"conference":"Eastern Conference","division":"Southeast Division"},{"id":"OKC","team":"Oklahoma City Thunder","seed":1,"wins":60,"loses":22,"win_percentage":0.732,"games_behind":0,"points_per_game":105.7,"points_allowed":96.5,"simple_rating_system":9.15,"conference":"Western Conference","division":"Northwest Division"},{"id":"DEN","team":"Denver Nuggets","seed":3,"wins":57,"loses":25,"win_percentage":0.695,"games_behind":3,"points_per_game":106.1,"points_allowed":101.1,"simple_rating_system":5.37,"conference":"Western Conference","division":"Northwest Division"},{"id":"UTA","team":"Utah Jazz","seed":9,"wins":43,"loses":39,"win_percentage":0.524,"games_behind":17,"points_per_game":98,"points_allowed":98.1,"simple_rating_system":0.3,"conference":"Western Conference","division":"Northwest Division"},{"id":"POR","team":"Portland Trail Blazers","seed":11,"wins":33,"loses":49,"win_percentage":0.402,"games_behind":27,"points_per_game":97.5,"points_allowed":100.7,"simple_rating_system":-2.53,"conference":"Western Conference","division":"Northwest Division"},{"id":"MIN","team":"Minnesota Timberwolves","seed":12,"wins":31,"loses":51,"win_percentage":0.378,"games_behind":29,"points_per_game":95.7,"points_allowed":98.1,"simple_rating_system":-1.83,"conference":"Western Conference","division":"Northwest Division"},{"id":"LAC","team":"Los Angeles Clippers","seed":4,"wins":56,"loses":26,"win_percentage":0.683,"games_behind":0,"points_per_game":101.1,"points_allowed":94.6,"simple_rating_system":6.43,"conference":"Western Conference","division":"Pacific Division"},{"id":"GSW","team":"Golden State Warriors","seed":6,"wins":47,"loses":35,"win_percentage":0.573,"games_behind":9,"points_per_game":101.2,"points_allowed":100.3,"simple_rating_system":1.32,"conference":"Western Conference","division":"Pacific Division"},{"id":"LAL","team":"Los Angeles Lakers","seed":7,"wins":45,"loses":37,"win_percentage":0.549,"games_behind":11,"points_per_game":102.2,"points_allowed":101,"simple_rating_system":1.48,"conference":"Western Conference","division":"Pacific Division"},{"id":"SAC","team":"Sacramento Kings","seed":13,"wins":28,"loses":54,"win_percentage":0.341,"games_behind":28,"points_per_game":100.2,"points_allowed":105.1,"simple_rating_system":-4.26,"conference":"Western Conference","division":"Pacific Division"},{"id":"PHO","team":"Phoenix Suns","seed":15,"wins":25,"loses":57,"win_percentage":0.305,"games_behind":31,"points_per_game":95.2,"points_allowed":101.6,"simple_rating_system":-5.75,"conference":"Western Conference","division":"Pacific Division"},{"id":"SAS","team":"San Antonio Spurs","seed":2,"wins":58,"loses":24,"win_percentage":0.707,"games_behind":0,"points_per_game":103,"points_allowed":96.6,"simple_rating_system":6.67,"conference":"Western Conference","division":"Southwest Division"},{"id":"MEM","team":"Memphis Grizzlies","seed":5,"wins":56,"loses":26,"win_percentage":0.683,"games_behind":2,"points_per_game":93.4,"points_allowed":89.3,"simple_rating_system":4.32,"conference":"Western Conference","division":"Southwest Division"},{"id":"HOU","team":"Houston Rockets","seed":8,"wins":45,"loses":37,"win_percentage":0.549,"games_behind":13,"points_per_game":106,"points_allowed":102.5,"simple_rating_system":3.69,"conference":"Western Conference","division":"Southwest Division"},{"id":"DAL","team":"Dallas Mavericks","seed":10,"wins":41,"loses":41,"win_percentage":0.5,"games_behind":17,"points_per_game":101.1,"points_allowed":101.7,"simple_rating_system":-0.24,"conference":"Western Conference","division":"Southwest Division"},{"id":"NOH","team":"New Orleans Hornets","seed":14,"wins":27,"loses":55,"win_percentage":0.329,"games_behind":31,"points_per_game":94.1,"points_allowed":97.9,"simple_rating_system":-3.12,"conference":"Western Conference","division":"Southwest Division"}]},{"year":2014,"standings":[{"id":"TOR","team":"Toronto Raptors","seed":3,"wins":48,"loses":34,"win_percentage":0.585,"games_behind":0,"points_per_game":101.3,"points_allowed":98,"simple_rating_system":2.55,"conference":"Eastern Conference","division":"Atlantic Division"},{"id":"BRK","team":"Brooklyn Nets","seed":5,"wins":44,"loses":38,"win_percentage":0.537,"games_behind":4,"points_per_game":98.5,"points_allowed":99.5,"simple_rating_system":-1.58,"conference":"Eastern Conference","division":"Atlantic Division"},{"id":"NYK","team":"New York Knicks","seed":9,"wins":37,"loses":45,"win_percentage":0.451,"games_behind":11,"points_per_game":98.6,"points_allowed":99.4,"simple_rating_system":-1.4,"conference":"Eastern Conference","division":"Atlantic Division"},{"id":"BOS","team":"Boston Celtics","seed":12,"wins":25,"loses":57,"win_percentage":0.305,"games_behind":23,"points_per_game":96.2,"points_allowed":100.7,"simple_rating_system":-4.97,"conference":"Eastern Conference","division":"Atlantic Division"},{"id":"PHI","team":"Philadelphia 76ers","seed":14,"wins":19,"loses":63,"win_percentage":0.232,"games_behind":29,"points_per_game":99.5,"points_allowed":109.9,"simple_rating_system":-10.66,"conference":"Eastern Conference","division":"Atlantic Division"},{"id":"IND","team":"Indiana Pacers","seed":1,"wins":56,"loses":26,"win_percentage":0.683,"games_behind":0,"points_per_game":96.7,"points_allowed":92.3,"simple_rating_system":3.63,"conference":"Eastern Conference","division":"Central Division"},{"id":"CHI","team":"Chicago Bulls","seed":3,"wins":48,"loses":34,"win_percentage":0.585,"games_behind":8,"points_per_game":93.7,"points_allowed":91.8,"simple_rating_system":1.2,"conference":"Eastern Conference","division":"Central Division"},{"id":"CLE","team":"Cleveland Cavaliers","seed":10,"wins":33,"loses":49,"win_percentage":0.402,"games_behind":23,"points_per_game":98.2,"points_allowed":101.5,"simple_rating_system":-3.86,"conference":"Eastern Conference","division":"Central Division"},{"id":"DET","team":"Detroit Pistons","seed":11,"wins":29,"loses":53,"win_percentage":0.354,"games_behind":27,"points_per_game":101,"points_allowed":104.7,"simple_rating_system":-4.13,"conference":"Eastern Conference","division":"Central Division"},{"id":"MIL","team":"Milwaukee Bucks","seed":15,"wins":15,"loses":67,"win_percentage":0.183,"games_behind":41,"points_per_game":95.5,"points_allowed":103.7,"simple_rating_system":-8.41,"conference":"Eastern Conference","division":"Central Division"},{"id":"MIA","team":"Miami Heat","seed":2,"wins":54,"loses":28,"win_percentage":0.659,"games_behind":0,"points_per_game":102.2,"points_allowed":97.4,"simple_rating_system":4.15,"conference":"Eastern Conference","division":"Southeast Division"},{"id":"WAS","team":"Washington Wizards","seed":5,"wins":44,"loses":38,"win_percentage":0.537,"games_behind":10,"points_per_game":100.7,"points_allowed":99.4,"simple_rating_system":0.48,"conference":"Eastern Conference","division":"Southeast Division"},{"id":"CHA","team":"Charlotte Bobcats","seed":7,"wins":43,"loses":39,"win_percentage":0.524,"games_behind":11,"points_per_game":96.9,"points_allowed":97.1,"simple_rating_system":-0.89,"conference":"Eastern Conference","division":"Southeast Division"},{"id":"ATL","team":"Atlanta Hawks","seed":8,"wins":38,"loses":44,"win_percentage":0.463,"games_behind":16,"points_per_game":101,"points_allowed":101.5,"simple_rating_system":-0.88,"conference":"Eastern Conference","division":"Southeast Division"},{"id":"ORL","team":"Orlando Magic","seed":13,"wins":23,"loses":59,"win_percentage":0.28,"games_behind":31,"points_per_game":96.5,"points_allowed":102,"simple_rating_system":-5.88,"conference":"Eastern Conference","division":"Southeast Division"},{"id":"OKC","team":"Oklahoma City Thunder","seed":2,"wins":59,"loses":23,"win_percentage":0.72,"games_behind":0,"points_per_game":106.2,"points_allowed":99.8,"simple_rating_system":6.66,"conference":"Western Conference","division":"Northwest Division"},{"id":"POR","team":"Portland Trail Blazers","seed":4,"wins":54,"loses":28,"win_percentage":0.659,"games_behind":5,"points_per_game":106.7,"points_allowed":102.8,"simple_rating_system":4.44,"conference":"Western Conference","division":"Northwest Division"},{"id":"MIN","team":"Minnesota Timberwolves","seed":10,"wins":40,"loses":42,"win_percentage":0.488,"games_behind":19,"points_per_game":106.9,"points_allowed":104.3,"simple_rating_system":3.1,"conference":"Western Conference","division":"Northwest Division"},{"id":"DEN","team":"Denver Nuggets","seed":11,"wins":36,"loses":46,"win_percentage":0.439,"games_behind":23,"points_per_game":104.4,"points_allowed":106.5,"simple_rating_system":-1.4,"conference":"Western Conference","division":"Northwest Division"},{"id":"UTA","team":"Utah Jazz","seed":15,"wins":25,"loses":57,"win_percentage":0.305,"games_behind":34,"points_per_game":95,"points_allowed":102.2,"simple_rating_system":-6.27,"conference":"Western Conference","division":"Northwest Division"},{"id":"LAC","team":"Los Angeles Clippers","seed":3,"wins":57,"loses":25,"win_percentage":0.695,"games_behind":0,"points_per_game":107.9,"points_allowed":101,"simple_rating_system":7.27,"conference":"Western Conference","division":"Pacific Division"},{"id":"GSW","team":"Golden State Warriors","seed":6,"wins":51,"loses":31,"win_percentage":0.622,"games_behind":6,"points_per_game":104.3,"points_allowed":99.5,"simple_rating_system":5.15,"conference":"Western Conference","division":"Pacific Division"},{"id":"PHO","team":"Phoenix Suns","seed":9,"wins":48,"loses":34,"win_percentage":0.585,"games_behind":9,"points_per_game":105.2,"points_allowed":102.6,"simple_rating_system":3.02,"conference":"Western Conference","division":"Pacific Division"},{"id":"SAC","team":"Sacramento Kings","seed":13,"wins":28,"loses":54,"win_percentage":0.341,"games_behind":29,"points_per_game":100.5,"points_allowed":103.4,"simple_rating_system":-2.08,"conference":"Western Conference","division":"Pacific Division"},{"id":"LAL","team":"Los Angeles Lakers","seed":14,"wins":27,"loses":55,"win_percentage":0.329,"games_behind":30,"points_per_game":103,"points_allowed":109.2,"simple_rating_system":-5.33,"conference":"Western Conference","division":"Pacific Division"},{"id":"SAS","team":"San Antonio Spurs","seed":1,"wins":62,"loses":20,"win_percentage":0.756,"games_behind":0,"points_per_game":105.4,"points_allowed":97.6,"simple_rating_system":8,"conference":"Western Conference","division":"Southwest Division"},{"id":"HOU","team":"Houston Rockets","seed":4,"wins":54,"loses":28,"win_percentage":0.659,"games_behind":8,"points_per_game":107.7,"points_allowed":103.1,"simple_rating_system":5.06,"conference":"Western Conference","division":"Southwest Division"},{"id":"MEM","team":"Memphis Grizzlies","seed":7,"wins":50,"loses":32,"win_percentage":0.61,"games_behind":12,"points_per_game":96.1,"points_allowed":94.6,"simple_rating_system":2.18,"conference":"Western Conference","division":"Southwest Division"},{"id":"DAL","team":"Dallas Mavericks","seed":8,"wins":49,"loses":33,"win_percentage":0.598,"games_behind":13,"points_per_game":104.8,"points_allowed":102.4,"simple_rating_system":2.91,"conference":"Western Conference","division":"Southwest Division"},{"id":"NOP","team":"New Orleans Pelicans","seed":12,"wins":34,"loses":48,"win_percentage":0.415,"games_behind":28,"points_per_game":99.7,"points_allowed":102.4,"simple_rating_system":-1.98,"conference":"Western Conference","division":"Southwest Division"}]}]